<?xml version="1.0" encoding="UTF-8"?>

<Career>
<Name>Vampire Hunter</Name>
  <WS>20</WS>
  <BS>20</BS>
  <S>10</S>
  <T>20</T>
  <Ag>15</Ag>
  <Int>15</Int>
  <WP>20</WP>
  <Fel>0</Fel>
  <A>1</A>
  <W>4</W>
  <SB>0</SB>
  <TB>0</TB>
  <M>0</M>
  <Mag>0</Mag>
  <IP>0</IP>
  <FP>0</FP>

  <Skills>Academic Knowledge (History) OR Academic Knowledge (Necromancy)</Skills>
  <Skills>Common Knowledge (the Empire)</Skills>
  <Skills>Concealment</Skills>
  <Skills>Dodge Blow</Skills>
  <Skills>Follow Trail</Skills>
  <Skills>Perception</Skills>
  <Skills>Scale Sheer Surface</Skills>
  <Skills>Shadowing</Skills>
  <Skills>Search</Skills>
  <Skills>Silent Move</Skills>
  <Skills>Speak Language (Classical)</Skills>

  <Talents>Mighty Shot OR Rapid Reload</Talents>
  <Talents>Specialist Weapon Group (Crossbow)</Talents>
  <Talents>Stout-hearted</Talents>
  <Talents>Strike Mighty Blow</Talents>
  <Talents>Strike to Injure</Talents>
  <Talents>Tunnel Rat</Talents>

  <Trappings>Repeater Crossbow with 10 Bolts</Trappings>
  <Trappings>Medfium Armour (Full Mail Shirt)</Trappings>
  <Trappings>Blessed Water</Trappings>
  <Trappings>4 Stakes</Trappings>

  <Exits>Demagogue</Exits>
  <Exits>Initiate</Exits>
  <Exits>Knight</Exits>
  <Exits>Targeteer</Exits>
  <Exits>Witch Hunter</Exits>
</Career>
